<?xml version='1.0' encoding='UTF-8'?>
<fingerprint>
  <timestamp>2015-05-20 09:35:06.578 UTC</timestamp>
  <md5sum>6393363b47ddcbba82321110c3e07519</md5sum>
  <fileName>org.hamcrest:hamcrest-core-1.3.jar</fileName>
  <usages>
    <entry>
      <string>passed_project</string>
      <ranges>1</ranges>
    </entry>
    <entry>
      <string>failed_project/groupId:ArticfactId</string>
      <ranges>1</ranges>
    </entry>
    <entry>
      <string>passed_project/utilitaires:mavenTest.artifactid</string>
      <ranges>1</ranges>
    </entry>
    <entry>
      <string>failed_project</string>
      <ranges>1</ranges>
    </entry>
  </usages>
  <facets/>
</fingerprint>